{
    "index": 0,
    "state": "<start_of_father_id>-1<end_of_father_id><start_of_local_id>0<end_of_local_id><start_of_thought><problem>George was selling some of his old toys on the internet. He managed to sell 3 little cars and a set of Legos. In total, he earned $45. How much did the Legos set cost, if one little car was sold for $5?<end_of_thought>",
    "parent": null,
    "visits": 4,
    "value": -0.11180511474609377,
    "policy_probs": [
        4.3371968786232173e-05,
        4.3371968786232173e-05,
        6.718064923916245e-06,
        6.718064923916245e-06,
        4.119436925975606e-05,
        4.119436925975606e-05
    ],
    "policy_entropy": [
        1.2560293674468994,
        1.3963509798049927,
        2.0065999031066895,
        0.9441401362419128,
        1.7647887468338013,
        1.8536667823791504
    ],
    "policy_varentropy": [
        2.3653464317321777,
        2.4078423976898193,
        3.642496347427368,
        1.5927870273590088,
        2.8035385608673096,
        2.8173105716705322
    ],
    "policy_cal_ready_texts": "",
    "value_cal_ready_texts": "",
    "true_value_from_tree": -12.433959502167847,
    "leaf_type": "",
    "rectify_visits": 6,
    "original_value": 0,
    "meta": "<problem>",
    "children": [
        {
            "index": 1,
            "state": "<refine>We have the equation $5k=45$, where k = 5 represents the total amount of cars George sold",
            "parent": 0,
            "visits": 1,
            "value": -0.47109375000000003,
            "policy_probs": [
                0.00014025018026586622,
                0.00014025018026586622
            ],
            "policy_entropy": [
                1.0420430898666382,
                1.4979337453842163
            ],
            "policy_varentropy": [
                1.7316786050796509,
                2.42588472366333
            ],
            "policy_cal_ready_texts": "",
            "value_cal_ready_texts": "",
            "true_value_from_tree": -13.815510557964274,
            "leaf_type": "failed",
            "rectify_visits": 1,
            "original_value": -0.00860595703125,
            "meta": "<refine>",
            "children": [
                {
                    "index": 2,
                    "state": "<critic>1. The equation $5k = 45$ is correctly solved for $k$, yielding $k = 9$. This indicates George made $9 \\times 5 = $45 in all sales of the cars, not a combined total of $45 including other purchases.2. Without additional informatio",
                    "parent": 1,
                    "visits": 0,
                    "value": -0.82421875,
                    "policy_probs": [],
                    "policy_entropy": [],
                    "policy_varentropy": [],
                    "policy_cal_ready_texts": "",
                    "value_cal_ready_texts": "",
                    "true_value_from_tree": null,
                    "leaf_type": "failed",
                    "rectify_visits": 0,
                    "original_value": -0.82421875,
                    "meta": "<critic>",
                    "children": []
                },
                {
                    "index": 3,
                    "state": "<expansion> Therefore the answer that the lego set cost $$30 is false, the remaining amount needs to be calculated from the correct equations given in the problem",
                    "parent": 1,
                    "visits": 0,
                    "value": -0.5234375,
                    "policy_probs": [],
                    "policy_entropy": [],
                    "policy_varentropy": [],
                    "policy_cal_ready_texts": "",
                    "value_cal_ready_texts": "",
                    "true_value_from_tree": null,
                    "leaf_type": "successful",
                    "rectify_visits": 0,
                    "original_value": -0.5234375,
                    "meta": "<expansion>",
                    "children": []
                }
            ]
        },
        {
            "index": 2,
            "state": "<expansion>\nYes. George sold 1 set of Little cars, and a set of Legos set, for a total combined cost of $5 + $<<2+3=5>>5.\n</expansion>\nGeorge then started selling some of his more valuable lego at a local online store where he made twenty time",
            "parent": 0,
            "visits": 0,
            "value": -0.38671875,
            "policy_probs": [],
            "policy_entropy": [],
            "policy_varentropy": [],
            "policy_cal_ready_texts": "",
            "value_cal_ready_texts": "",
            "true_value_from_tree": -13.815510557964274,
            "leaf_type": "failed",
            "rectify_visits": 1,
            "original_value": -0.38671875,
            "meta": "<expansion>",
            "children": []
        },
        {
            "index": 3,
            "state": "<refine>The equation \"a cars on the car board and one car on the online car trade-in equals 3 Little cars and/or a LegoSet,\" has not quite worked well for this level, though the intention to use it could be the starting point for a good system",
            "parent": 0,
            "visits": 0,
            "value": -0.16015625,
            "policy_probs": [],
            "policy_entropy": [],
            "policy_varentropy": [],
            "policy_cal_ready_texts": "",
            "value_cal_ready_texts": "",
            "true_value_from_tree": -13.815510557964274,
            "leaf_type": "failed",
            "rectify_visits": 1,
            "original_value": -0.16015625,
            "meta": "<refine>",
            "children": []
        },
        {
            "index": 4,
            "state": "<expansion>George sold 3 cars, which cost 3 * $5 = $15",
            "parent": 0,
            "visits": 0,
            "value": -0.474609375,
            "policy_probs": [],
            "policy_entropy": [],
            "policy_varentropy": [],
            "policy_cal_ready_texts": "",
            "value_cal_ready_texts": "",
            "true_value_from_tree": -13.815510557964274,
            "leaf_type": "failed",
            "rectify_visits": 1,
            "original_value": -0.474609375,
            "meta": "<expansion>",
            "children": []
        },
        {
            "index": 5,
            "state": "<refine>Ok, all we have to solve is 3+5t1:45 dollars",
            "parent": 0,
            "visits": 0,
            "value": -0.2255859375,
            "policy_probs": [],
            "policy_entropy": [],
            "policy_varentropy": [],
            "policy_cal_ready_texts": "",
            "value_cal_ready_texts": "",
            "true_value_from_tree": -13.815510557964274,
            "leaf_type": "failed",
            "rectify_visits": 1,
            "original_value": -0.2255859375,
            "meta": "<refine>",
            "children": []
        },
        {
            "index": 6,
            "state": "<expansion>The Lego set cost 30 dollars, but that's not true because George sold 3 little cars instead of Legos set at that amount and bought lego pieces at twice $5 in total amount sold each item of lego at its set-price instead making a case distinction. How much higher would it have ha",
            "parent": 0,
            "visits": 0,
            "value": -1.5,
            "policy_probs": [],
            "policy_entropy": [],
            "policy_varentropy": [],
            "policy_cal_ready_texts": "",
            "value_cal_ready_texts": "",
            "true_value_from_tree": -13.815510557964274,
            "leaf_type": "failed",
            "rectify_visits": 1,
            "original_value": -1.5,
            "meta": "<expansion>",
            "children": []
        }
    ]
}